Workbook

Sheet Leads
A1: Lead ID | B1: Date received | C1: Source | D1: Customer name | E1: Phone | F1: Contact via | G1: Service requested | H1: Pickup location (zip/city) | I1: Drop-off location | J1: Move date | K1: Helpers | L1: Photos received? (Y/N) | M1: Quoted price $ | N1: Qualified? (Y/N) | O1: Quote sent (date) | P1: Status | Q1: Booked date | R1: Job done (date) | S1: Revenue $ | T1: Review asked? | U1: Referral source | V1: Notes
A2: L001 | B2: 46312 | C2: Craigslist | D2: EXAMPLE – delete | E2: 305-000-0000 | F2: SMS | G2: Unload U-Haul | H2: 33020 Hollywood | I2: same | J2: 46320 | K2: 1 | L2: Y | M2: 150 | N2: Y | O2: 46312 | P2: Quoted | T2: N

Sheet Campaign Log
A1: Date | B1: Channel | C1: Where (sub-area / group / ad set) | D1: Title / angle | E1: Cost $ | F1: Live until | G1: Leads attributed | H1: Notes
B2: Craigslist | C2: brw – services > labor/move | D2: Angle 1 – Text me first | E2: 5 | H2: Status: NOT POSTED – awaiting approval
B3: Facebook ad | C3: 25 mi radius – WhatsApp objective | D3: Angle 1 creative | E3: 10 | H3: Status: NOT LAUNCHED – awaiting approval

Sheet Weekly Scorecard
A1: Week start | B1: Money spent $ | C1: Leads | D1: Qualified leads | E1: Quotes sent | F1: Jobs booked | G1: Revenue $ | H1: Cost / lead $ | I1: Cost / booked job $ | J1: Best source | K1: Notes
A2: 46315 | B2: =SUMIFS('Campaign Log'!E:E,'Campaign Log'!A:A,">="&A2,'Campaign Log'!A:A,"<"&A2+7) | C2: =COUNTIFS(Leads!B:B,">="&A2,Leads!B:B,"<"&A2+7) | D2: =COUNTIFS(Leads!B:B,">="&A2,Leads!B:B,"<"&A2+7,Leads!N:N,"Y") | E2: =COUNTIFS(Leads!O:O,">="&A2,Leads!O:O,"<"&A2+7) | F2: =COUNTIFS(Leads!Q:Q,">="&A2,Leads!Q:Q,"<"&A2+7) | G2: =SUMIFS(Leads!S:S,Leads!R:R,">="&A2,Leads!R:R,"<"&A2+7) | H2: =IF(C2>0,B2/C2,"") | I2: =IF(F2>0,B2/F2,"")
A3: =A2+7 | B3: =SUMIFS('Campaign Log'!E:E,'Campaign Log'!A:A,">="&A3,'Campaign Log'!A:A,"<"&A3+7) | C3: =COUNTIFS(Leads!B:B,">="&A3,Leads!B:B,"<"&A3+7) | D3: =COUNTIFS(Leads!B:B,">="&A3,Leads!B:B,"<"&A3+7,Leads!N:N,"Y") | E3: =COUNTIFS(Leads!O:O,">="&A3,Leads!O:O,"<"&A3+7) | F3: =COUNTIFS(Leads!Q:Q,">="&A3,Leads!Q:Q,"<"&A3+7) | G3: =SUMIFS(Leads!S:S,Leads!R:R,">="&A3,Leads!R:R,"<"&A3+7) | H3: =IF(C3>0,B3/C3,"") | I3: =IF(F3>0,B3/F3,"")
A4: =A3+7 | B4: =SUMIFS('Campaign Log'!E:E,'Campaign Log'!A:A,">="&A4,'Campaign Log'!A:A,"<"&A4+7) | C4: =COUNTIFS(Leads!B:B,">="&A4,Leads!B:B,"<"&A4+7) | D4: =COUNTIFS(Leads!B:B,">="&A4,Leads!B:B,"<"&A4+7,Leads!N:N,"Y") | E4: =COUNTIFS(Leads!O:O,">="&A4,Leads!O:O,"<"&A4+7) | F4: =COUNTIFS(Leads!Q:Q,">="&A4,Leads!Q:Q,"<"&A4+7) | G4: =SUMIFS(Leads!S:S,Leads!R:R,">="&A4,Leads!R:R,"<"&A4+7) | H4: =IF(C4>0,B4/C4,"") | I4: =IF(F4>0,B4/F4,"")
A5: =A4+7 | B5: =SUMIFS('Campaign Log'!E:E,'Campaign Log'!A:A,">="&A5,'Campaign Log'!A:A,"<"&A5+7) | C5: =COUNTIFS(Leads!B:B,">="&A5,Leads!B:B,"<"&A5+7) | D5: =COUNTIFS(Leads!B:B,">="&A5,Leads!B:B,"<"&A5+7,Leads!N:N,"Y") | E5: =COUNTIFS(Leads!O:O,">="&A5,Leads!O:O,"<"&A5+7) | F5: =COUNTIFS(Leads!Q:Q,">="&A5,Leads!Q:Q,"<"&A5+7) | G5: =SUMIFS(Leads!S:S,Leads!R:R,">="&A5,Leads!R:R,"<"&A5+7) | H5: =IF(C5>0,B5/C5,"") | I5: =IF(F5>0,B5/F5,"")
A6: =A5+7 | B6: =SUMIFS('Campaign Log'!E:E,'Campaign Log'!A:A,">="&A6,'Campaign Log'!A:A,"<"&A6+7) | C6: =COUNTIFS(Leads!B:B,">="&A6,Leads!B:B,"<"&A6+7) | D6: =COUNTIFS(Leads!B:B,">="&A6,Leads!B:B,"<"&A6+7,Leads!N:N,"Y") | E6: =COUNTIFS(Leads!O:O,">="&A6,Leads!O:O,"<"&A6+7) | F6: =COUNTIFS(Leads!Q:Q,">="&A6,Leads!Q:Q,"<"&A6+7) | G6: =SUMIFS(Leads!S:S,Leads!R:R,">="&A6,Leads!R:R,"<"&A6+7) | H6: =IF(C6>0,B6/C6,"") | I6: =IF(F6>0,B6/F6,"")
A7: =A6+7 | B7: =SUMIFS('Campaign Log'!E:E,'Campaign Log'!A:A,">="&A7,'Campaign Log'!A:A,"<"&A7+7) | C7: =COUNTIFS(Leads!B:B,">="&A7,Leads!B:B,"<"&A7+7) | D7: =COUNTIFS(Leads!B:B,">="&A7,Leads!B:B,"<"&A7+7,Leads!N:N,"Y") | E7: =COUNTIFS(Leads!O:O,">="&A7,Leads!O:O,"<"&A7+7) | F7: =COUNTIFS(Leads!Q:Q,">="&A7,Leads!Q:Q,"<"&A7+7) | G7: =SUMIFS(Leads!S:S,Leads!R:R,">="&A7,Leads!R:R,"<"&A7+7) | H7: =IF(C7>0,B7/C7,"") | I7: =IF(F7>0,B7/F7,"")
A8: =A7+7 | B8: =SUMIFS('Campaign Log'!E:E,'Campaign Log'!A:A,">="&A8,'Campaign Log'!A:A,"<"&A8+7) | C8: =COUNTIFS(Leads!B:B,">="&A8,Leads!B:B,"<"&A8+7) | D8: =COUNTIFS(Leads!B:B,">="&A8,Leads!B:B,"<"&A8+7,Leads!N:N,"Y") | E8: =COUNTIFS(Leads!O:O,">="&A8,Leads!O:O,"<"&A8+7) | F8: =COUNTIFS(Leads!Q:Q,">="&A8,Leads!Q:Q,"<"&A8+7) | G8: =SUMIFS(Leads!S:S,Leads!R:R,">="&A8,Leads!R:R,"<"&A8+7) | H8: =IF(C8>0,B8/C8,"") | I8: =IF(F8>0,B8/F8,"")
A9: =A8+7 | B9: =SUMIFS('Campaign Log'!E:E,'Campaign Log'!A:A,">="&A9,'Campaign Log'!A:A,"<"&A9+7) | C9: =COUNTIFS(Leads!B:B,">="&A9,Leads!B:B,"<"&A9+7) | D9: =COUNTIFS(Leads!B:B,">="&A9,Leads!B:B,"<"&A9+7,Leads!N:N,"Y") | E9: =COUNTIFS(Leads!O:O,">="&A9,Leads!O:O,"<"&A9+7) | F9: =COUNTIFS(Leads!Q:Q,">="&A9,Leads!Q:Q,"<"&A9+7) | G9: =SUMIFS(Leads!S:S,Leads!R:R,">="&A9,Leads!R:R,"<"&A9+7) | H9: =IF(C9>0,B9/C9,"") | I9: =IF(F9>0,B9/F9,"")
A10: =A9+7 | B10: =SUMIFS('Campaign Log'!E:E,'Campaign Log'!A:A,">="&A10,'Campaign Log'!A:A,"<"&A10+7) | C10: =COUNTIFS(Leads!B:B,">="&A10,Leads!B:B,"<"&A10+7) | D10: =COUNTIFS(Leads!B:B,">="&A10,Leads!B:B,"<"&A10+7,Leads!N:N,"Y") | E10: =COUNTIFS(Leads!O:O,">="&A10,Leads!O:O,"<"&A10+7) | F10: =COUNTIFS(Leads!Q:Q,">="&A10,Leads!Q:Q,"<"&A10+7) | G10: =SUMIFS(Leads!S:S,Leads!R:R,">="&A10,Leads!R:R,"<"&A10+7) | H10: =IF(C10>0,B10/C10,"") | I10: =IF(F10>0,B10/F10,"")
A11: =A10+7 | B11: =SUMIFS('Campaign Log'!E:E,'Campaign Log'!A:A,">="&A11,'Campaign Log'!A:A,"<"&A11+7) | C11: =COUNTIFS(Leads!B:B,">="&A11,Leads!B:B,"<"&A11+7) | D11: =COUNTIFS(Leads!B:B,">="&A11,Leads!B:B,"<"&A11+7,Leads!N:N,"Y") | E11: =COUNTIFS(Leads!O:O,">="&A11,Leads!O:O,"<"&A11+7) | F11: =COUNTIFS(Leads!Q:Q,">="&A11,Leads!Q:Q,"<"&A11+7) | G11: =SUMIFS(Leads!S:S,Leads!R:R,">="&A11,Leads!R:R,"<"&A11+7) | H11: =IF(C11>0,B11/C11,"") | I11: =IF(F11>0,B11/F11,"")
A12: =A11+7 | B12: =SUMIFS('Campaign Log'!E:E,'Campaign Log'!A:A,">="&A12,'Campaign Log'!A:A,"<"&A12+7) | C12: =COUNTIFS(Leads!B:B,">="&A12,Leads!B:B,"<"&A12+7) | D12: =COUNTIFS(Leads!B:B,">="&A12,Leads!B:B,"<"&A12+7,Leads!N:N,"Y") | E12: =COUNTIFS(Leads!O:O,">="&A12,Leads!O:O,"<"&A12+7) | F12: =COUNTIFS(Leads!Q:Q,">="&A12,Leads!Q:Q,"<"&A12+7) | G12: =SUMIFS(Leads!S:S,Leads!R:R,">="&A12,Leads!R:R,"<"&A12+7) | H12: =IF(C12>0,B12/C12,"") | I12: =IF(F12>0,B12/F12,"")
A13: =A12+7 | B13: =SUMIFS('Campaign Log'!E:E,'Campaign Log'!A:A,">="&A13,'Campaign Log'!A:A,"<"&A13+7) | C13: =COUNTIFS(Leads!B:B,">="&A13,Leads!B:B,"<"&A13+7) | D13: =COUNTIFS(Leads!B:B,">="&A13,Leads!B:B,"<"&A13+7,Leads!N:N,"Y") | E13: =COUNTIFS(Leads!O:O,">="&A13,Leads!O:O,"<"&A13+7) | F13: =COUNTIFS(Leads!Q:Q,">="&A13,Leads!Q:Q,"<"&A13+7) | G13: =SUMIFS(Leads!S:S,Leads!R:R,">="&A13,Leads!R:R,"<"&A13+7) | H13: =IF(C13>0,B13/C13,"") | I13: =IF(F13>0,B13/F13,"")
A14: =A13+7 | B14: =SUMIFS('Campaign Log'!E:E,'Campaign Log'!A:A,">="&A14,'Campaign Log'!A:A,"<"&A14+7) | C14: =COUNTIFS(Leads!B:B,">="&A14,Leads!B:B,"<"&A14+7) | D14: =COUNTIFS(Leads!B:B,">="&A14,Leads!B:B,"<"&A14+7,Leads!N:N,"Y") | E14: =COUNTIFS(Leads!O:O,">="&A14,Leads!O:O,"<"&A14+7) | F14: =COUNTIFS(Leads!Q:Q,">="&A14,Leads!Q:Q,"<"&A14+7) | G14: =SUMIFS(Leads!S:S,Leads!R:R,">="&A14,Leads!R:R,"<"&A14+7) | H14: =IF(C14>0,B14/C14,"") | I14: =IF(F14>0,B14/F14,"")
... A53: =A52+7 | B53: =SUMIFS('Campaign Log'!E:E,'Campaign Log'!A:A,">="&A53,'Campaign Log'!A:A,"<"&A53+7) | C53: =COUNTIFS(Leads!B:B,">="&A53,Leads!B:B,"<"&A53+7) | D53: =COUNTIFS(Leads!B:B,">="&A53,Leads!B:B,"<"&A53+7,Leads!N:N,"Y") | E53: =COUNTIFS(Leads!O:O,">="&A53,Leads!O:O,"<"&A53+7) | F53: =COUNTIFS(Leads!Q:Q,">="&A53,Leads!Q:Q,"<"&A53+7) | G53: =SUMIFS(Leads!S:S,Leads!R:R,">="&A53,Leads!R:R,"<"&A53+7) | H53: =IF(C53>0,B53/C53,"") | I53: =IF(F53>0,B53/F53,"")

Sheet Source Performance
A1: Source | B1: Leads | C1: Qualified | D1: Booked | E1: Revenue $ | F1: Spend $ | G1: Cost / booked job $
A2: Craigslist | B2: =COUNTIF(Leads!C:C,A2) | C2: =COUNTIFS(Leads!C:C,A2,Leads!N:N,"Y") | D2: =COUNTIFS(Leads!C:C,A2,Leads!P:P,"Booked")+COUNTIFS(Leads!C:C,A2,Leads!P:P,"Done") | E2: =SUMIF(Leads!C:C,A2,Leads!S:S) | F2: =SUMIF('Campaign Log'!B:B,A2,'Campaign Log'!E:E) | G2: =IF(D2>0,F2/D2,"")
A3: Facebook group | B3: =COUNTIF(Leads!C:C,A3) | C3: =COUNTIFS(Leads!C:C,A3,Leads!N:N,"Y") | D3: =COUNTIFS(Leads!C:C,A3,Leads!P:P,"Booked")+COUNTIFS(Leads!C:C,A3,Leads!P:P,"Done") | E3: =SUMIF(Leads!C:C,A3,Leads!S:S) | F3: =SUMIF('Campaign Log'!B:B,A3,'Campaign Log'!E:E) | G3: =IF(D3>0,F3/D3,"")
A4: Facebook ad | B4: =COUNTIF(Leads!C:C,A4) | C4: =COUNTIFS(Leads!C:C,A4,Leads!N:N,"Y") | D4: =COUNTIFS(Leads!C:C,A4,Leads!P:P,"Booked")+COUNTIFS(Leads!C:C,A4,Leads!P:P,"Done") | E4: =SUMIF(Leads!C:C,A4,Leads!S:S) | F4: =SUMIF('Campaign Log'!B:B,A4,'Campaign Log'!E:E) | G4: =IF(D4>0,F4/D4,"")
A5: Facebook Marketplace | B5: =COUNTIF(Leads!C:C,A5) | C5: =COUNTIFS(Leads!C:C,A5,Leads!N:N,"Y") | D5: =COUNTIFS(Leads!C:C,A5,Leads!P:P,"Booked")+COUNTIFS(Leads!C:C,A5,Leads!P:P,"Done") | E5: =SUMIF(Leads!C:C,A5,Leads!S:S) | F5: =SUMIF('Campaign Log'!B:B,A5,'Campaign Log'!E:E) | G5: =IF(D5>0,F5/D5,"")
A6: Nextdoor | B6: =COUNTIF(Leads!C:C,A6) | C6: =COUNTIFS(Leads!C:C,A6,Leads!N:N,"Y") | D6: =COUNTIFS(Leads!C:C,A6,Leads!P:P,"Booked")+COUNTIFS(Leads!C:C,A6,Leads!P:P,"Done") | E6: =SUMIF(Leads!C:C,A6,Leads!S:S) | F6: =SUMIF('Campaign Log'!B:B,A6,'Campaign Log'!E:E) | G6: =IF(D6>0,F6/D6,"")
A7: Google | B7: =COUNTIF(Leads!C:C,A7) | C7: =COUNTIFS(Leads!C:C,A7,Leads!N:N,"Y") | D7: =COUNTIFS(Leads!C:C,A7,Leads!P:P,"Booked")+COUNTIFS(Leads!C:C,A7,Leads!P:P,"Done") | E7: =SUMIF(Leads!C:C,A7,Leads!S:S) | F7: =SUMIF('Campaign Log'!B:B,A7,'Campaign Log'!E:E) | G7: =IF(D7>0,F7/D7,"")
A8: U-Haul Moving Help | B8: =COUNTIF(Leads!C:C,A8) | C8: =COUNTIFS(Leads!C:C,A8,Leads!N:N,"Y") | D8: =COUNTIFS(Leads!C:C,A8,Leads!P:P,"Booked")+COUNTIFS(Leads!C:C,A8,Leads!P:P,"Done") | E8: =SUMIF(Leads!C:C,A8,Leads!S:S) | F8: =SUMIF('Campaign Log'!B:B,A8,'Campaign Log'!E:E) | G8: =IF(D8>0,F8/D8,"")
A9: TaskRabbit | B9: =COUNTIF(Leads!C:C,A9) | C9: =COUNTIFS(Leads!C:C,A9,Leads!N:N,"Y") | D9: =COUNTIFS(Leads!C:C,A9,Leads!P:P,"Booked")+COUNTIFS(Leads!C:C,A9,Leads!P:P,"Done") | E9: =SUMIF(Leads!C:C,A9,Leads!S:S) | F9: =SUMIF('Campaign Log'!B:B,A9,'Campaign Log'!E:E) | G9: =IF(D9>0,F9/D9,"")
A10: Referral | B10: =COUNTIF(Leads!C:C,A10) | C10: =COUNTIFS(Leads!C:C,A10,Leads!N:N,"Y") | D10: =COUNTIFS(Leads!C:C,A10,Leads!P:P,"Booked")+COUNTIFS(Leads!C:C,A10,Leads!P:P,"Done") | E10: =SUMIF(Leads!C:C,A10,Leads!S:S) | F10: =SUMIF('Campaign Log'!B:B,A10,'Campaign Log'!E:E) | G10: =IF(D10>0,F10/D10,"")
A11: Partner | B11: =COUNTIF(Leads!C:C,A11) | C11: =COUNTIFS(Leads!C:C,A11,Leads!N:N,"Y") | D11: =COUNTIFS(Leads!C:C,A11,Leads!P:P,"Booked")+COUNTIFS(Leads!C:C,A11,Leads!P:P,"Done") | E11: =SUMIF(Leads!C:C,A11,Leads!S:S) | F11: =SUMIF('Campaign Log'!B:B,A11,'Campaign Log'!E:E) | G11: =IF(D11>0,F11/D11,"")
A12: Repeat | B12: =COUNTIF(Leads!C:C,A12) | C12: =COUNTIFS(Leads!C:C,A12,Leads!N:N,"Y") | D12: =COUNTIFS(Leads!C:C,A12,Leads!P:P,"Booked")+COUNTIFS(Leads!C:C,A12,Leads!P:P,"Done") | E12: =SUMIF(Leads!C:C,A12,Leads!S:S) | F12: =SUMIF('Campaign Log'!B:B,A12,'Campaign Log'!E:E) | G12: =IF(D12>0,F12/D12,"")
A13: Other | B13: =COUNTIF(Leads!C:C,A13) | C13: =COUNTIFS(Leads!C:C,A13,Leads!N:N,"Y") | D13: =COUNTIFS(Leads!C:C,A13,Leads!P:P,"Booked")+COUNTIFS(Leads!C:C,A13,Leads!P:P,"Done") | E13: =SUMIF(Leads!C:C,A13,Leads!S:S) | F13: =SUMIF('Campaign Log'!B:B,A13,'Campaign Log'!E:E) | G13: =IF(D13>0,F13/D13,"")

Sheet Follow-up Rules
A1: When | B1: Action | C1: Template (07-templates/customer-reply-templates.md)
A2: New lead arrives | B2: Reply within 5 minutes, ask the 5 quote questions | C2: T1 First reply
A3: Info received | B3: Send price same conversation | C3: T2 Quote
A4: Quote sent, no answer 4 h | B4: One nudge | C4: T3 Nudge
A5: Quote sent, no answer 24 h | B5: Final nudge, then mark 'No response' | C5: T4 Final nudge
A6: Booked | B6: Confirm date/time/address/payment | C6: T5 Booking confirmation
A7: Day before job | B7: Reminder | C7: T6 Reminder
A8: Job done | B8: Thank + ask for review/referral | C8: T7 Review ask
A9: 30 days after job | B9: Check-in for referrals | C9: T8 Referral check-in
